<?xml version="1.0" encoding="utf-8"?>
<!DOCTYPE Map[]>
<Map srs="+proj=merc +a=6378137 +b=6378137 +lat_ts=0.0 +lon_0=0.0 +x_0=0.0 +y_0=0.0 +k=1.0 +units=m +nadgrids=@null +wktext +no_defs +over">

<Parameters>
  <Parameter name="center">-75.1642,39.9582,13</Parameter>
  <Parameter name="format">pbf</Parameter>
  <Parameter name="json"><![CDATA[{"vector_layers":[{"id":"transit-stations","description":"In-city transit stations","fields":{"name":"String","id":"Number","type":"String","desc":"String","Distance":"String","More Info":"String","lon":"Number","lat":"Number","Stations":"String","Tickets":"String","Fare":"String","Hours":"String","Accessible?":"String"}},{"id":"screens","description":"Jumbotron screens for viewing Sunday's Papal Mass","fields":{"name":"String","id":"Number","type":"String","desc":"String","Distance":"String","More Info":"String","lon":"Number","lat":"Number","Stations":"String","Tickets":"String","Fare":"String","Hours":"String","Accessible?":"String"}},{"id":"entrances_labels","description":"","fields":{"cartodb_id":"Number","name":"String","description":"String","ticketed":"String"}},{"id":"bikeride","description":"","fields":{"stroke":"String","stroke-width":"Number","stroke-opacity":"Number","name":"String","marker-size":"String","marker-color":"String","marker-symbol":"String"}},{"id":"walking_paths","description":"","fields":{"cartodb_id":"Number","name":"String","description":"String"}}]}]]></Parameter>
  <Parameter name="maxzoom">15</Parameter>
  <Parameter name="minzoom">13</Parameter>
  <Parameter name="name"><![CDATA[Transit & Screens]]></Parameter>
</Parameters>


<Layer name="transit-stations"
  buffer-size="8"
  srs="+proj=longlat +ellps=WGS84 +datum=WGS84 +no_defs">
    
    <Datasource>
       <Parameter name="file"><![CDATA[/Users/lancona/Downloads/transit-stations.csv]]></Parameter>
       <Parameter name="type"><![CDATA[csv]]></Parameter>
    </Datasource>
  </Layer>

<Layer name="screens"
  buffer-size="8"
  srs="+proj=longlat +ellps=WGS84 +datum=WGS84 +no_defs">
    
    <Datasource>
       <Parameter name="file"><![CDATA[/Users/lancona/Documents/Github/laurenancona/philly-pope-map/data/screens.csv]]></Parameter>
       <Parameter name="type"><![CDATA[csv]]></Parameter>
    </Datasource>
  </Layer>

<Layer name="entrances_labels"
  buffer-size="8"
  srs="+proj=longlat +ellps=WGS84 +datum=WGS84 +no_defs">
    
    <Datasource>
       <Parameter name="file"><![CDATA[/Users/lancona/Documents/Github/laurenancona/philly-pope-map/data/entrances_labels.geojson]]></Parameter>
       <Parameter name="layer"><![CDATA[OGRGeoJSON]]></Parameter>
       <Parameter name="type"><![CDATA[ogr]]></Parameter>
    </Datasource>
  </Layer>

<Layer name="bikeride"
  buffer-size="8"
  srs="+proj=longlat +ellps=WGS84 +datum=WGS84 +no_defs">
    
    <Datasource>
       <Parameter name="file"><![CDATA[/Users/lancona/Documents/Github/laurenancona/philly-pope-map/data/bikeride.geojson]]></Parameter>
       <Parameter name="layer"><![CDATA[OGRGeoJSON]]></Parameter>
       <Parameter name="type"><![CDATA[ogr]]></Parameter>
    </Datasource>
  </Layer>

<Layer name="walking_paths"
  buffer-size="8"
  srs="+proj=longlat +ellps=WGS84 +datum=WGS84 +no_defs">
    
    <Datasource>
       <Parameter name="file"><![CDATA[/Users/lancona/Documents/Github/laurenancona/philly-pope-map/data/walking_paths.geojson]]></Parameter>
       <Parameter name="layer"><![CDATA[OGRGeoJSON]]></Parameter>
       <Parameter name="type"><![CDATA[ogr]]></Parameter>
    </Datasource>
  </Layer>

</Map>